setup.py
traveler_api_factory.py
Traveler_API.egg-info/PKG-INFO
Traveler_API.egg-info/SOURCES.txt
Traveler_API.egg-info/dependency_links.txt
Traveler_API.egg-info/requires.txt
Traveler_API.egg-info/top_level.txt
travelerApi/__init__.py
travelerApi/api_client.py
travelerApi/configuration.py
travelerApi/exceptions.py
travelerApi/rest.py
travelerApi/api/__init__.py
travelerApi/api/binder_api.py
travelerApi/api/data_api.py
travelerApi/api/form_api.py
travelerApi/api/traveler_api.py
travelerApi/models/__init__.py
travelerApi/models/binder.py
travelerApi/models/binder_add_work_options.py
travelerApi/models/binder_all_of.py
travelerApi/models/binder_create_options.py
travelerApi/models/binder_remove_work_options.py
travelerApi/models/binder_work.py
travelerApi/models/binder_work_all_of.py
travelerApi/models/data.py
travelerApi/models/data_all_of.py
travelerApi/models/discrepancy_form.py
travelerApi/models/discrepancy_form_all_of.py
travelerApi/models/discrepancy_log.py
travelerApi/models/discrepancy_log_all_of.py
travelerApi/models/discrepancy_log_record.py
travelerApi/models/discrepancy_log_record_all_of.py
travelerApi/models/form.py
travelerApi/models/form_all_of.py
travelerApi/models/form_create_options.py
travelerApi/models/form_reference.py
travelerApi/models/form_reference_all_of.py
travelerApi/models/form_reference_object.py
travelerApi/models/form_reference_object_all_of.py
travelerApi/models/man_power.py
travelerApi/models/man_power_all_of.py
travelerApi/models/released_form.py
travelerApi/models/released_form_all_of.py
travelerApi/models/released_form_reference.py
travelerApi/models/released_form_reference_all_of.py
travelerApi/models/traveler.py
travelerApi/models/traveler_all_of.py
travelerApi/models/traveler_change_archive_options.py
travelerApi/models/traveler_create_options.py
travelerApi/models/traveler_data.py
travelerApi/models/traveler_data_all_of.py
travelerApi/models/traveler_data_note_object.py
travelerApi/models/traveler_data_note_object_all_of.py
travelerApi/models/traveler_data_options.py
travelerApi/models/traveler_data_upload_options.py
travelerApi/models/traveler_discrepancy.py
travelerApi/models/traveler_key_object.py
