Metadata-Version: 2.1
Name: Traveler-API
Version: 1.6.4.post1
Summary: Python APIs used to communicate with traveler API.
Home-page: https://github.com/AdvancedPhotonSource/traveler
Maintainer: Dariusz Jarosz
Maintainer-email: djarosz@aps.anl.gov
License: Copyright (c) 2015 Dong Liu, Dariusz Jarosz
